mrce/__init__.py
mrce/run.py
mrce/task_generator.py
mrce/task_runner.py
mrce/config/config.json
mrce/config/dev_config.json
mrce/config/prod_config.json
mrce_plus-1.0.0.dist-info/licenses/LICENSE
mrce_plus-1.0.0.dist-info/METADATA
mrce_plus-1.0.0.dist-info/WHEEL
mrce_plus-1.0.0.dist-info/top_level.txt
mrce_plus-1.0.0.dist-info/RECORD
