Metadata-Version: 2.4
Name: mrce-plus
Version: 1.0.0
Summary: Meta-Recursive Cognitive Engine Plus - A triple-loop cognitive system with multi-tiered memory and LLM integration
Home-page: https://github.com/krishnabajpai/mrce-plus
Author: Krishna Bajpai, Vedanshi Gupta
Author-email: Krishna Bajpai <krishna@krishnabajpai.me>, Vedanshi Gupta <vedanshigupta158@gmail.com>
License: MIT
Project-URL: Homepage, https://github.com/krishnabajpai/mrce-plus
Project-URL: Bug Tracker, https://github.com/krishnabajpai/mrce-plus/issues
Classifier: Development Status :: 4 - Beta
Classifier: Intended Audience :: Developers
Classifier: Intended Audience :: Science/Research
Classifier: License :: OSI Approved :: MIT License
Classifier: Programming Language :: Python :: 3
Classifier: Programming Language :: Python :: 3.8
Classifier: Programming Language :: Python :: 3.9
Classifier: Programming Language :: Python :: 3.10
Classifier: Programming Language :: Python :: 3.11
Classifier: Topic :: Scientific/Engineering :: Artificial Intelligence
Requires-Python: >=3.8
License-File: LICENSE
Requires-Dist: numpy>=1.19.0
Requires-Dist: scipy>=1.7.0
Requires-Dist: networkx>=2.6.0
Requires-Dist: openai>=0.27.0
Requires-Dist: transformers>=4.21.0
Requires-Dist: torch>=1.10.0
Requires-Dist: sentencepiece>=0.1.96
Requires-Dist: accelerate>=0.16.0
Requires-Dist: tiktoken>=0.3.3
Requires-Dist: pymongo>=4.0.0
Requires-Dist: sqlalchemy>=1.4.0
Requires-Dist: redis>=4.3.0
Requires-Dist: ray>=2.0.0
Requires-Dist: pydantic>=1.9.0
Requires-Dist: prometheus-client>=0.14.0
Requires-Dist: psutil>=5.9.0
Requires-Dist: tqdm>=4.62.0
Requires-Dist: python-dotenv>=0.20.0
Requires-Dist: tenacity>=8.0.0
Requires-Dist: requests>=2.28.0
Requires-Dist: colorlog>=6.7.0
Requires-Dist: cryptography>=37.0.0
Requires-Dist: pytest>=7.0.0
Requires-Dist: black>=22.3.0
Requires-Dist: flake8>=5.0.0
Requires-Dist: mypy>=0.961
Dynamic: author
Dynamic: home-page
Dynamic: license-file
Dynamic: requires-python
